code_scalpel/__init__.py
code_scalpel/cli.py
code_scalpel/code_analyzer.py
code_scalpel/core.py
code_scalpel/project_crawler.py
code_scalpel/surgical_extractor.py
code_scalpel/surgical_patcher.py
code_scalpel/agents/__init__.py
code_scalpel/agents/base_agent.py
code_scalpel/agents/code_review_agent.py
code_scalpel/agents/optimazation_agent.py
code_scalpel/agents/security_agent.py
code_scalpel/ast_tools/__init__.py
code_scalpel/ast_tools/analyzer.py
code_scalpel/ast_tools/builder.py
code_scalpel/ast_tools/call_graph.py
code_scalpel/ast_tools/cross_file_extractor.py
code_scalpel/ast_tools/dependency_parser.py
code_scalpel/ast_tools/import_resolver.py
code_scalpel/ast_tools/osv_client.py
code_scalpel/ast_tools/transformer.py
code_scalpel/ast_tools/utils.py
code_scalpel/ast_tools/validator.py
code_scalpel/ast_tools/visualizer.py
code_scalpel/autonomy/README.md
code_scalpel/autonomy/__init__.py
code_scalpel/autonomy/audit.py
code_scalpel/autonomy/engine.py
code_scalpel/autonomy/error_to_diff.py
code_scalpel/autonomy/fix_loop.py
code_scalpel/autonomy/mutation_gate.py
code_scalpel/autonomy/sandbox.py
code_scalpel/autonomy/stubs.py
code_scalpel/autonomy/integrations/__init__.py
code_scalpel/autonomy/integrations/autogen.py
code_scalpel/autonomy/integrations/crewai.py
code_scalpel/autonomy/integrations/langgraph.py
code_scalpel/cache/__init__.py
code_scalpel/cache/analysis_cache.py
code_scalpel/cache/ast_cache.py
code_scalpel/cache/incremental_analyzer.py
code_scalpel/cache/parallel_parser.py
code_scalpel/code_parser/__init__.py
code_scalpel/code_parser/base_parser.py
code_scalpel/code_parser/factory.py
code_scalpel/code_parser/interface.py
code_scalpel/code_parser/python_parser.py
code_scalpel/code_parser/cpp_parsers/cpp_parsers_Clang-Static-Analyzer.py
code_scalpel/code_parser/cpp_parsers/cpp_parsers_Cppcheck.py
code_scalpel/code_parser/cpp_parsers/cpp_parsers_SonarQube.py
code_scalpel/code_parser/csharp_parsers/csharp_parsers_ReSharper.py
code_scalpel-3.0.1.dist-info/METADATA
code_scalpel-3.0.1.dist-info/WHEEL
code_scalpel-3.0.1.dist-info/entry_points.txt
code_scalpel-3.0.1.dist-info/licenses/LICENSE
code_scalpel-3.0.1.dist-info/RECORD
