Metadata-Version: 2.4
Name: code-scalpel
Version: 3.0.1
Summary: MCP server toolkit for AI agents - surgical code analysis and modification
Project-URL: Homepage, https://github.com/tescolopio/code-scalpel
Project-URL: Documentation, https://github.com/tescolopio/code-scalpel#readme
Project-URL: Repository, https://github.com/tescolopio/code-scalpel.git
Project-URL: Issues, https://github.com/tescolopio/code-scalpel/issues
Project-URL: Changelog, https://github.com/tescolopio/code-scalpel/releases
Author-email: Tim Escolopio <3dtsus@gmail.com>
License: MIT
License-File: LICENSE
Keywords: ai-agents,ast,autogen,code-analysis,crewai,mcp,pdg,static-analysis,symbolic-execution
Classifier: Development Status :: 5 - Production/Stable
Classifier: Intended Audience :: Developers
Classifier: License :: OSI Approved :: MIT License
Classifier: Programming Language :: Python :: 3
Classifier: Programming Language :: Python :: 3.10
Classifier: Programming Language :: Python :: 3.11
Classifier: Programming Language :: Python :: 3.12
Classifier: Programming Language :: Python :: 3.13
Classifier: Topic :: Software Development :: Quality Assurance
Requires-Python: >=3.10
Requires-Dist: astor>=0.8.1
Requires-Dist: flask>=2.0.0
Requires-Dist: graphviz>=0.16
Requires-Dist: mcp>=1.23.0
Requires-Dist: networkx>=2.6.3
Requires-Dist: structlog>=24.1.0
Requires-Dist: tomli>=2.0.0; python_version < '3.11'
Requires-Dist: tree-sitter-java>=0.21.0
Requires-Dist: tree-sitter-javascript>=0.21.0
Requires-Dist: tree-sitter-typescript>=0.21.0
Requires-Dist: tree-sitter>=0.21.0
Requires-Dist: urllib3>=2.6.0
Requires-Dist: z3-solver>=4.8.12
Provides-Extra: all
Requires-Dist: anthropic>=0.18.0; extra == 'all'
Requires-Dist: crewai>=0.1.0; extra == 'all'
Requires-Dist: langchain>=0.1.0; extra == 'all'
Requires-Dist: openai>=1.0.0; extra == 'all'
Requires-Dist: pyautogen>=0.2.0; extra == 'all'
Requires-Dist: tree-sitter-javascript>=0.21.0; extra == 'all'
Requires-Dist: tree-sitter-typescript>=0.21.0; extra == 'all'
Requires-Dist: tree-sitter>=0.21.0; extra == 'all'
Provides-Extra: autogen
Requires-Dist: pyautogen>=0.2.0; extra == 'autogen'
Provides-Extra: crewai
Requires-Dist: crewai>=0.1.0; extra == 'crewai'
Provides-Extra: dev
Requires-Dist: black>=24.0.0; extra == 'dev'
Requires-Dist: build>=1.0.0; extra == 'dev'
Requires-Dist: mypy>=1.0.0; extra == 'dev'
Requires-Dist: pytest-asyncio>=0.21.0; extra == 'dev'
Requires-Dist: pytest-cov>=4.0.0; extra == 'dev'
Requires-Dist: pytest>=7.0.0; extra == 'dev'
Requires-Dist: ruff>=0.4.0; extra == 'dev'
Requires-Dist: twine>=4.0.0; extra == 'dev'
Provides-Extra: langchain
Requires-Dist: langchain>=0.1.0; extra == 'langchain'
Provides-Extra: polyglot
Requires-Dist: tree-sitter-java>=0.21.0; extra == 'polyglot'
Requires-Dist: tree-sitter-javascript>=0.21.0; extra == 'polyglot'
Requires-Dist: tree-sitter-typescript>=0.21.0; extra == 'polyglot'
Requires-Dist: tree-sitter>=0.21.0; extra == 'polyglot'
